[{"index":788,"State":"Andhra Pradesh","Type":"Unemployed","Total":767},{"index":789,"State":"Andhra Pradesh","Type":"Student","Total":559},{"index":790,"State":"Andhra Pradesh","Type":"Private Service","Total":1453},{"index":791,"State":"Andhra Pradesh","Type":"Government Service","Total":137},{"index":792,"State":"Andhra Pradesh","Type":"Self-employed","Total":751},{"index":793,"State":"Andhra Pradesh","Type":"Retired Person","Total":84},{"index":794,"State":"Andhra Pradesh","Type":"Public Sector Undertaking","Total":331},{"index":795,"State":"Andhra Pradesh","Type":"Professional Activity","Total":365},{"index":796,"State":"Andhra Pradesh","Type":"House Wife","Total":2143},{"index":797,"State":"Andhra Pradesh","Type":"Farmers","Total":2572},{"index":798,"State":"Arunachal Pradesh","Type":"Unemployed","Total":16},{"index":799,"State":"Arunachal Pradesh","Type":"Student","Total":13},{"index":800,"State":"Arunachal Pradesh","Type":"Private Service","Total":30},{"index":801,"State":"Arunachal Pradesh","Type":"Government Service","Total":9},{"index":802,"State":"Arunachal Pradesh","Type":"Public Sector Undertaking","Total":2},{"index":803,"State":"Arunachal Pradesh","Type":"House Wife","Total":19},{"index":804,"State":"Arunachal Pradesh","Type":"Farmers","Total":11},{"index":805,"State":"Assam","Type":"Unemployed","Total":68},{"index":806,"State":"Assam","Type":"Student","Total":221},{"index":807,"State":"Assam","Type":"Private Service","Total":133},{"index":808,"State":"Assam","Type":"Government Service","Total":54},{"index":809,"State":"Assam","Type":"Self-employed","Total":353},{"index":810,"State":"Assam","Type":"Retired Person","Total":4},{"index":811,"State":"Assam","Type":"Public Sector Undertaking","Total":116},{"index":812,"State":"Assam","Type":"Professional Activity","Total":125},{"index":813,"State":"Assam","Type":"House Wife","Total":403},{"index":814,"State":"Assam","Type":"Farmers","Total":344},{"index":815,"State":"Bihar","Type":"Unemployed","Total":14},{"index":816,"State":"Bihar","Type":"Student","Total":64},{"index":817,"State":"Bihar","Type":"Private Service","Total":24},{"index":818,"State":"Bihar","Type":"Government Service","Total":15},{"index":819,"State":"Bihar","Type":"Self-employed","Total":3},{"index":820,"State":"Bihar","Type":"Retired Person","Total":1},{"index":821,"State":"Bihar","Type":"Professional Activity","Total":1},{"index":822,"State":"Bihar","Type":"House Wife","Total":130},{"index":823,"State":"Bihar","Type":"Farmers","Total":68},{"index":831,"State":"Chhattisgarh","Type":"Unemployed","Total":359},{"index":832,"State":"Chhattisgarh","Type":"Student","Total":290},{"index":833,"State":"Chhattisgarh","Type":"Private Service","Total":406},{"index":834,"State":"Chhattisgarh","Type":"Government Service","Total":66},{"index":835,"State":"Chhattisgarh","Type":"Self-employed","Total":110},{"index":836,"State":"Chhattisgarh","Type":"Retired Person","Total":17},{"index":837,"State":"Chhattisgarh","Type":"Public Sector Undertaking","Total":10},{"index":838,"State":"Chhattisgarh","Type":"Professional Activity","Total":229},{"index":839,"State":"Chhattisgarh","Type":"House Wife","Total":779},{"index":840,"State":"Chhattisgarh","Type":"Farmers","Total":4},{"index":851,"State":"Delhi (Ut)","Type":"Unemployed","Total":369},{"index":852,"State":"Delhi (Ut)","Type":"Student","Total":266},{"index":853,"State":"Delhi (Ut)","Type":"Private Service","Total":280},{"index":854,"State":"Delhi (Ut)","Type":"Government Service","Total":25},{"index":855,"State":"Delhi (Ut)","Type":"Self-employed","Total":44},{"index":856,"State":"Delhi (Ut)","Type":"Retired Person","Total":17},{"index":857,"State":"Delhi (Ut)","Type":"Public Sector Undertaking","Total":41},{"index":858,"State":"Delhi (Ut)","Type":"Professional Activity","Total":10},{"index":859,"State":"Delhi (Ut)","Type":"House Wife","Total":355},{"index":860,"State":"Delhi (Ut)","Type":"Farmers","Total":21},{"index":861,"State":"Goa","Type":"Unemployed","Total":49},{"index":862,"State":"Goa","Type":"Student","Total":23},{"index":863,"State":"Goa","Type":"Private Service","Total":55},{"index":864,"State":"Goa","Type":"Government Service","Total":10},{"index":865,"State":"Goa","Type":"Self-employed","Total":18},{"index":866,"State":"Goa","Type":"Retired Person","Total":5},{"index":867,"State":"Goa","Type":"Public Sector Undertaking","Total":8},{"index":868,"State":"Goa","Type":"Professional Activity","Total":4},{"index":869,"State":"Goa","Type":"House Wife","Total":55},{"index":870,"State":"Goa","Type":"Farmers","Total":1},{"index":871,"State":"Gujarat","Type":"Unemployed","Total":557},{"index":872,"State":"Gujarat","Type":"Student","Total":388},{"index":873,"State":"Gujarat","Type":"Private Service","Total":895},{"index":874,"State":"Gujarat","Type":"Government Service","Total":91},{"index":875,"State":"Gujarat","Type":"Self-employed","Total":269},{"index":876,"State":"Gujarat","Type":"Retired Person","Total":186},{"index":877,"State":"Gujarat","Type":"Public Sector Undertaking","Total":150},{"index":878,"State":"Gujarat","Type":"Professional Activity","Total":510},{"index":879,"State":"Gujarat","Type":"House Wife","Total":1795},{"index":880,"State":"Gujarat","Type":"Farmers","Total":564},{"index":881,"State":"Haryana","Type":"Unemployed","Total":327},{"index":882,"State":"Haryana","Type":"Student","Total":142},{"index":883,"State":"Haryana","Type":"Private Service","Total":247},{"index":884,"State":"Haryana","Type":"Government Service","Total":51},{"index":885,"State":"Haryana","Type":"Self-employed","Total":45},{"index":886,"State":"Haryana","Type":"Retired Person","Total":3},{"index":887,"State":"Haryana","Type":"Public Sector Undertaking","Total":57},{"index":888,"State":"Haryana","Type":"Professional Activity","Total":41},{"index":889,"State":"Haryana","Type":"House Wife","Total":389},{"index":890,"State":"Haryana","Type":"Farmers","Total":276},{"index":891,"State":"Himachal Pradesh","Type":"Unemployed","Total":44},{"index":892,"State":"Himachal Pradesh","Type":"Student","Total":47},{"index":893,"State":"Himachal Pradesh","Type":"Private Service","Total":39},{"index":894,"State":"Himachal Pradesh","Type":"Government Service","Total":10},{"index":895,"State":"Himachal Pradesh","Type":"Self-employed","Total":36},{"index":896,"State":"Himachal Pradesh","Type":"Retired Person","Total":3},{"index":897,"State":"Himachal Pradesh","Type":"Public Sector Undertaking","Total":28},{"index":898,"State":"Himachal Pradesh","Type":"Professional Activity","Total":8},{"index":899,"State":"Himachal Pradesh","Type":"House Wife","Total":80},{"index":900,"State":"Himachal Pradesh","Type":"Farmers","Total":29},{"index":901,"State":"Jammu & Kashmir","Type":"Unemployed","Total":53},{"index":902,"State":"Jammu & Kashmir","Type":"Student","Total":62},{"index":903,"State":"Jammu & Kashmir","Type":"Private Service","Total":18},{"index":904,"State":"Jammu & Kashmir","Type":"Government Service","Total":24},{"index":905,"State":"Jammu & Kashmir","Type":"Self-employed","Total":10},{"index":906,"State":"Jammu & Kashmir","Type":"Retired Person","Total":5},{"index":907,"State":"Jammu & Kashmir","Type":"Professional Activity","Total":11},{"index":908,"State":"Jammu & Kashmir","Type":"House Wife","Total":75},{"index":909,"State":"Jammu & Kashmir","Type":"Farmers","Total":10},{"index":910,"State":"Jharkhand","Type":"Unemployed","Total":158},{"index":911,"State":"Jharkhand","Type":"Student","Total":175},{"index":912,"State":"Jharkhand","Type":"Private Service","Total":89},{"index":913,"State":"Jharkhand","Type":"Government Service","Total":19},{"index":914,"State":"Jharkhand","Type":"Self-employed","Total":65},{"index":915,"State":"Jharkhand","Type":"Retired Person","Total":3},{"index":916,"State":"Jharkhand","Type":"Public Sector Undertaking","Total":19},{"index":917,"State":"Jharkhand","Type":"Professional Activity","Total":22},{"index":918,"State":"Jharkhand","Type":"House Wife","Total":212},{"index":919,"State":"Jharkhand","Type":"Farmers","Total":119},{"index":920,"State":"Karnataka","Type":"Unemployed","Total":715},{"index":921,"State":"Karnataka","Type":"Student","Total":560},{"index":922,"State":"Karnataka","Type":"Private Service","Total":1261},{"index":923,"State":"Karnataka","Type":"Government Service","Total":203},{"index":924,"State":"Karnataka","Type":"Self-employed","Total":642},{"index":925,"State":"Karnataka","Type":"Retired Person","Total":69},{"index":926,"State":"Karnataka","Type":"Public Sector Undertaking","Total":342},{"index":927,"State":"Karnataka","Type":"Professional Activity","Total":301},{"index":928,"State":"Karnataka","Type":"House Wife","Total":1850},{"index":929,"State":"Karnataka","Type":"Farmers","Total":1875},{"index":930,"State":"Kerala","Type":"Unemployed","Total":753},{"index":931,"State":"Kerala","Type":"Student","Total":263},{"index":932,"State":"Kerala","Type":"Private Service","Total":563},{"index":933,"State":"Kerala","Type":"Government Service","Total":61},{"index":934,"State":"Kerala","Type":"Self-employed","Total":479},{"index":935,"State":"Kerala","Type":"Retired Person","Total":90},{"index":936,"State":"Kerala","Type":"Public Sector Undertaking","Total":82},{"index":937,"State":"Kerala","Type":"Professional Activity","Total":172},{"index":938,"State":"Kerala","Type":"House Wife","Total":1194},{"index":939,"State":"Kerala","Type":"Farmers","Total":1081},{"index":940,"State":"Madhya Pradesh","Type":"Unemployed","Total":442},{"index":941,"State":"Madhya Pradesh","Type":"Student","Total":595},{"index":942,"State":"Madhya Pradesh","Type":"Private Service","Total":698},{"index":943,"State":"Madhya Pradesh","Type":"Government Service","Total":100},{"index":944,"State":"Madhya Pradesh","Type":"Self-employed","Total":469},{"index":945,"State":"Madhya Pradesh","Type":"Retired Person","Total":29},{"index":946,"State":"Madhya Pradesh","Type":"Public Sector Undertaking","Total":174},{"index":947,"State":"Madhya Pradesh","Type":"Professional Activity","Total":463},{"index":948,"State":"Madhya Pradesh","Type":"House Wife","Total":2740},{"index":949,"State":"Madhya Pradesh","Type":"Farmers","Total":1172},{"index":950,"State":"Maharashtra","Type":"Unemployed","Total":964},{"index":951,"State":"Maharashtra","Type":"Student","Total":921},{"index":952,"State":"Maharashtra","Type":"Private Service","Total":2264},{"index":953,"State":"Maharashtra","Type":"Government Service","Total":189},{"index":954,"State":"Maharashtra","Type":"Self-employed","Total":577},{"index":955,"State":"Maharashtra","Type":"Retired Person","Total":146},{"index":956,"State":"Maharashtra","Type":"Public Sector Undertaking","Total":222},{"index":957,"State":"Maharashtra","Type":"Professional Activity","Total":429},{"index":958,"State":"Maharashtra","Type":"House Wife","Total":3350},{"index":959,"State":"Maharashtra","Type":"Farmers","Total":3786},{"index":960,"State":"Manipur","Type":"Student","Total":14},{"index":961,"State":"Manipur","Type":"Government Service","Total":5},{"index":962,"State":"Manipur","Type":"House Wife","Total":9},{"index":963,"State":"Meghalaya","Type":"Unemployed","Total":23},{"index":964,"State":"Meghalaya","Type":"Student","Total":25},{"index":965,"State":"Meghalaya","Type":"Private Service","Total":5},{"index":966,"State":"Meghalaya","Type":"Government Service","Total":4},{"index":967,"State":"Meghalaya","Type":"Self-employed","Total":18},{"index":968,"State":"Meghalaya","Type":"Public Sector Undertaking","Total":1},{"index":969,"State":"Meghalaya","Type":"Professional Activity","Total":3},{"index":970,"State":"Meghalaya","Type":"House Wife","Total":14},{"index":971,"State":"Meghalaya","Type":"Farmers","Total":10},{"index":972,"State":"Mizoram","Type":"Unemployed","Total":66},{"index":973,"State":"Mizoram","Type":"Student","Total":7},{"index":974,"State":"Mizoram","Type":"Private Service","Total":20},{"index":975,"State":"Mizoram","Type":"Government Service","Total":2},{"index":976,"State":"Mizoram","Type":"Self-employed","Total":39},{"index":977,"State":"Mizoram","Type":"Retired Person","Total":4},{"index":978,"State":"Mizoram","Type":"House Wife","Total":1},{"index":979,"State":"Mizoram","Type":"Farmers","Total":10},{"index":980,"State":"Nagaland","Type":"Unemployed","Total":1},{"index":981,"State":"Nagaland","Type":"Student","Total":4},{"index":982,"State":"Nagaland","Type":"Government Service","Total":6},{"index":983,"State":"Nagaland","Type":"Self-employed","Total":3},{"index":984,"State":"Nagaland","Type":"Professional Activity","Total":3},{"index":985,"State":"Nagaland","Type":"House Wife","Total":3},{"index":986,"State":"Nagaland","Type":"Farmers","Total":9},{"index":987,"State":"Odisha","Type":"Unemployed","Total":554},{"index":988,"State":"Odisha","Type":"Student","Total":423},{"index":989,"State":"Odisha","Type":"Private Service","Total":487},{"index":990,"State":"Odisha","Type":"Government Service","Total":64},{"index":991,"State":"Odisha","Type":"Self-employed","Total":416},{"index":992,"State":"Odisha","Type":"Retired Person","Total":60},{"index":993,"State":"Odisha","Type":"Public Sector Undertaking","Total":127},{"index":994,"State":"Odisha","Type":"Professional Activity","Total":163},{"index":995,"State":"Odisha","Type":"House Wife","Total":870},{"index":996,"State":"Odisha","Type":"Farmers","Total":146},{"index":1006,"State":"Punjab","Type":"Unemployed","Total":90},{"index":1007,"State":"Punjab","Type":"Student","Total":57},{"index":1008,"State":"Punjab","Type":"Private Service","Total":181},{"index":1009,"State":"Punjab","Type":"Government Service","Total":14},{"index":1010,"State":"Punjab","Type":"Self-employed","Total":39},{"index":1011,"State":"Punjab","Type":"Retired Person","Total":8},{"index":1012,"State":"Punjab","Type":"Public Sector Undertaking","Total":17},{"index":1013,"State":"Punjab","Type":"Professional Activity","Total":25},{"index":1014,"State":"Punjab","Type":"House Wife","Total":173},{"index":1015,"State":"Punjab","Type":"Farmers","Total":75},{"index":1016,"State":"Rajasthan","Type":"Unemployed","Total":175},{"index":1017,"State":"Rajasthan","Type":"Student","Total":240},{"index":1018,"State":"Rajasthan","Type":"Private Service","Total":398},{"index":1019,"State":"Rajasthan","Type":"Government Service","Total":53},{"index":1020,"State":"Rajasthan","Type":"Self-employed","Total":178},{"index":1021,"State":"Rajasthan","Type":"Retired Person","Total":11},{"index":1022,"State":"Rajasthan","Type":"Public Sector Undertaking","Total":44},{"index":1023,"State":"Rajasthan","Type":"Professional Activity","Total":97},{"index":1024,"State":"Rajasthan","Type":"House Wife","Total":894},{"index":1025,"State":"Rajasthan","Type":"Farmers","Total":270},{"index":1026,"State":"Sikkim","Type":"Unemployed","Total":19},{"index":1027,"State":"Sikkim","Type":"Student","Total":20},{"index":1028,"State":"Sikkim","Type":"Private Service","Total":22},{"index":1029,"State":"Sikkim","Type":"Government Service","Total":23},{"index":1030,"State":"Sikkim","Type":"Self-employed","Total":15},{"index":1031,"State":"Sikkim","Type":"Public Sector Undertaking","Total":10},{"index":1032,"State":"Sikkim","Type":"Professional Activity","Total":11},{"index":1033,"State":"Sikkim","Type":"House Wife","Total":22},{"index":1034,"State":"Sikkim","Type":"Farmers","Total":19},{"index":1035,"State":"Tamil Nadu","Type":"Unemployed","Total":1938},{"index":1036,"State":"Tamil Nadu","Type":"Student","Total":795},{"index":1037,"State":"Tamil Nadu","Type":"Private Service","Total":1047},{"index":1038,"State":"Tamil Nadu","Type":"Government Service","Total":284},{"index":1039,"State":"Tamil Nadu","Type":"Self-employed","Total":801},{"index":1040,"State":"Tamil Nadu","Type":"Retired Person","Total":71},{"index":1041,"State":"Tamil Nadu","Type":"Public Sector Undertaking","Total":258},{"index":1042,"State":"Tamil Nadu","Type":"Professional Activity","Total":220},{"index":1043,"State":"Tamil Nadu","Type":"House Wife","Total":2911},{"index":1044,"State":"Tamil Nadu","Type":"Farmers","Total":499},{"index":1045,"State":"Tripura","Type":"Unemployed","Total":28},{"index":1046,"State":"Tripura","Type":"Student","Total":76},{"index":1047,"State":"Tripura","Type":"Private Service","Total":6},{"index":1048,"State":"Tripura","Type":"Government Service","Total":2},{"index":1049,"State":"Tripura","Type":"Self-employed","Total":55},{"index":1050,"State":"Tripura","Type":"Professional Activity","Total":6},{"index":1051,"State":"Tripura","Type":"House Wife","Total":128},{"index":1052,"State":"Tripura","Type":"Farmers","Total":18},{"index":1053,"State":"Uttar Pradesh","Type":"Unemployed","Total":246},{"index":1054,"State":"Uttar Pradesh","Type":"Student","Total":305},{"index":1055,"State":"Uttar Pradesh","Type":"Private Service","Total":470},{"index":1056,"State":"Uttar Pradesh","Type":"Government Service","Total":89},{"index":1057,"State":"Uttar Pradesh","Type":"Self-employed","Total":227},{"index":1058,"State":"Uttar Pradesh","Type":"Retired Person","Total":10},{"index":1059,"State":"Uttar Pradesh","Type":"Public Sector Undertaking","Total":56},{"index":1060,"State":"Uttar Pradesh","Type":"Professional Activity","Total":130},{"index":1061,"State":"Uttar Pradesh","Type":"House Wife","Total":1077},{"index":1062,"State":"Uttar Pradesh","Type":"Farmers","Total":745},{"index":1063,"State":"Uttarakhand","Type":"Unemployed","Total":26},{"index":1064,"State":"Uttarakhand","Type":"Student","Total":20},{"index":1065,"State":"Uttarakhand","Type":"Private Service","Total":47},{"index":1066,"State":"Uttarakhand","Type":"Government Service","Total":7},{"index":1067,"State":"Uttarakhand","Type":"Self-employed","Total":20},{"index":1068,"State":"Uttarakhand","Type":"Public Sector Undertaking","Total":8},{"index":1069,"State":"Uttarakhand","Type":"Professional Activity","Total":1},{"index":1070,"State":"Uttarakhand","Type":"House Wife","Total":63},{"index":1071,"State":"Uttarakhand","Type":"Farmers","Total":14}]